test/__init__.py
test/test_coordinate_offsets.py
test/test_keplerian_field.py
test/test_vgrad.py
velocity_tools/__init__.py
velocity_tools/coordinate_offsets.py
velocity_tools/keplerian_field.py
velocity_tools/stream_lines.py
velocity_tools/vgrad.py
velocity_tools-1.1.dist-info/METADATA
velocity_tools-1.1.dist-info/WHEEL
velocity_tools-1.1.dist-info/top_level.txt
velocity_tools-1.1.dist-info/RECORD
