Metadata-Version: 2.4
Name: velocity_tools
Version: 1.1
Summary: Tools to help analysis of velocity cubes and velocity fields.
Author-email: "Jaime E. Pineda" <jpineda@mpe.mpg.de>
Maintainer-email: "Jaime E. Pineda" <jpineda@mpe.mpg.de>
License: MIT License
Project-URL: Homepage, https://github.com/jpinedaf/velocity-tools
Requires-Python: >=3.7
Requires-Dist: importlib-resources; python_version < "3.9"
Requires-Dist: astropy>=5.0
Requires-Dist: scipy>=1.7
Requires-Dist: numpy>=1.21
Requires-Dist: matplotlib>=3.4
Requires-Dist: scikit-image>=0.9
Requires-Dist: spectral-cube>=0.5
Requires-Dist: radio-beam>=0.3
